AllUtils/__init__.py
AllUtils/auto_utils/__init__.py
AllUtils/auto_utils/auto_click/__init__.py
AllUtils/auto_utils/auto_click/auto_click_by_image_utils.py
AllUtils/auto_utils/auto_click/auto_click_by_point_utils.py
AllUtils/auto_utils/auto_click/positions.json
AllUtils/auto_utils/moniter/__init__.py
AllUtils/auto_utils/moniter/moniter_keyboard_utils.py
AllUtils/crawler_utils/__init__.py
AllUtils/crawler_utils/crawler_utils.py
AllUtils/crawler_utils/curl_convert.js
AllUtils/crawler_utils/webpackmodules_extractor.js
AllUtils/data_structure_utils/__init__.py
AllUtils/data_structure_utils/data_structure_utils.py
AllUtils/database_utils/__init__.py
AllUtils/database_utils/database_utils.py
AllUtils/decorator_utils/__init__.py
AllUtils/decorator_utils/decorator_utils.py
AllUtils/deep_learning_utils/__init__.py
AllUtils/deep_learning_utils/CNN_utils/__init__.py
AllUtils/deep_learning_utils/CNN_utils/test.py
AllUtils/deep_learning_utils/CNN_utils/train_test.py
AllUtils/deep_learning_utils/CNN_utils/train_val_test_dataloaders.py
AllUtils/deep_learning_utils/CNN_utils/img_CNN_utils/__init__.py
AllUtils/deep_learning_utils/CNN_utils/img_CNN_utils/data_partition.py
AllUtils/deep_learning_utils/CNN_utils/img_CNN_utils/predict.py
AllUtils/deep_learning_utils/CNN_utils/img_CNN_utils/train_val_test_dataloader.py
AllUtils/deep_learning_utils/CNN_utils/str_CNN_utils/__init__.py
AllUtils/deep_learning_utils/CNN_utils/str_CNN_utils/train_val_test_dataloader.py
AllUtils/engineer_measure_utils/__init__.py
AllUtils/engineer_measure_utils/coordinate_utils.py
AllUtils/engineer_measure_utils/decimal_to_any.py
AllUtils/engineer_measure_utils/dms_degrees.py
AllUtils/engineer_measure_utils/new_round.py
AllUtils/excel_word_utils/__init__.py
AllUtils/excel_word_utils/excel_utils.py
AllUtils/excel_word_utils/word_utils.py
AllUtils/image_utils/__init__.py
AllUtils/image_utils/image_utils.py
AllUtils/meta_class_utils/__init__.py
AllUtils/meta_class_utils/meta_class_utils.py
AllUtils-1.0.1.dist-info/METADATA
AllUtils-1.0.1.dist-info/WHEEL
AllUtils-1.0.1.dist-info/top_level.txt
AllUtils-1.0.1.dist-info/RECORD
