Metadata-Version: 2.1
Name: AllUtils
Version: 1.0.1
Summary: A light weight command line menu that supports Windows, MacOS, and Linux
Author: kyw
Author-email: 
Keywords: python
Classifier: Development Status :: 1 - Planning
Classifier: Intended Audience :: Developers
Classifier: Programming Language :: Python :: 3
Classifier: Operating System :: Unix
Classifier: Operating System :: MacOS :: MacOS X
Classifier: Operating System :: Microsoft :: Windows
Requires-Dist: lxml
Requires-Dist: itchat
Requires-Dist: twilio
Requires-Dist: qq
Requires-Dist: colorama
Requires-Dist: matplotlib
Requires-Dist: numpy
Requires-Dist: scipy
Requires-Dist: opencv-python
Requires-Dist: openpyxl
Requires-Dist: psutil
Requires-Dist: python-docx
Requires-Dist: mysql-connector-python
Requires-Dist: comtypes
Requires-Dist: sortedcontainers
Requires-Dist: pynput
Requires-Dist: pywinauto
Requires-Dist: pywin32
Requires-Dist: Pillow
Requires-Dist: loguru
Requires-Dist: keyboard
